metashovel/__init__.py
metashovel/cli.py
metashovel/client.py
metashovel/helpers.py
metashovel/metabase_io.py
metashovel/splitter.py
metashovel/metabase/__init__.py
metashovel/metabase/client.py
metashovel/metabase/helpers.py
metashovel/metabase/metabase_io.py
metashovel/metabase/splitter.py
metashovel-0.4.1.dist-info/METADATA
metashovel-0.4.1.dist-info/WHEEL
metashovel-0.4.1.dist-info/entry_points.txt
metashovel-0.4.1.dist-info/top_level.txt
metashovel-0.4.1.dist-info/RECORD
