Metadata-Version: 2.1
Name: metashovel
Version: 0.4.1
Summary: CLI tool to import and export Metabase items (questions, dashboards, collections) across instances
Home-page: https://gitlab.wemove.eu/campeval/metashovel
Author: Romain Thouvenin, Marcin Koziej
Author-email: romain@wemove.eu, marcin@cahoots.pl
License: UNKNOWN
Platform: UNKNOWN
Classifier: Programming Language :: Python :: 3
Classifier: License :: OSI Approved :: MIT License
Classifier: Operating System :: OS Independent
Requires-Dist: click
Requires-Dist: metabase (>=1.4.5)
Requires-Dist: pyaml
Requires-Dist: slug
